setup.py
buoyantBoussinesqPisoFlux/__init__.py
buoyantBoussinesqPisoFlux.egg-info/PKG-INFO
buoyantBoussinesqPisoFlux.egg-info/SOURCES.txt
buoyantBoussinesqPisoFlux.egg-info/dependency_links.txt
buoyantBoussinesqPisoFlux.egg-info/entry_points.txt
buoyantBoussinesqPisoFlux.egg-info/requires.txt
buoyantBoussinesqPisoFlux.egg-info/top_level.txt
buoyantBoussinesqPisoFlux.egg-info/zip-safe
buoyantBoussinesqPisoFlux/r1_6/__init__.py
buoyantBoussinesqPisoFlux/r1_6_dev/__init__.py